[
  {
    "subject": "ml",
    "level": "level1",
    "status": "failed",
    "timestamp": "2025-10-29T14:38:04.641443",
    "answers": [
      {
        "questionId": "LR_003",
        "partId": "Data Exploration & Missing Values",
        "code": "import pandas as pd\r\ndf=pd.read_csv('')",
        "passed": false
      },
      {
        "questionId": "LR_003",
        "partId": "Feature Scaling & Preprocessing",
        "code": "",
        "passed": false
      },
      {
        "questionId": "LR_003",
        "partId": "Model Training & Hyperparameter Tuning",
        "code": "",
        "passed": false
      },
      {
        "questionId": "LR_003",
        "partId": "Model Evaluation,Interpretation of Coefficients",
        "code": "",
        "passed": false
      }
    ]
  }
]